datetimeutc/__init__.py
datetimeutc/fields.py
django_datetime_utc-1.0.6.dist-info/METADATA
django_datetime_utc-1.0.6.dist-info/WHEEL
django_datetime_utc-1.0.6.dist-info/licenses/LICENSE
django_datetime_utc-1.0.6.dist-info/RECORD
