Metadata-Version: 2.4
Name: django-datetime-utc
Version: 1.0.6
Summary: Django UTC datetime field - timestamp without time zone
License: MIT
License-File: LICENSE
Keywords: django,timestamp without time zone,utc,datetime
Author: Darren O'Neill
Author-email: darren@pixeldomain.co.uk
Requires-Python: >=3.12,<4.0
Classifier: Environment :: Web Environment
Classifier: Framework :: Django
Classifier: Intended Audience :: Developers
Classifier: License :: OSI Approved :: MIT License
Classifier: Programming Language :: Python :: 3
Classifier: Programming Language :: Python :: 3.12
Classifier: Programming Language :: Python :: 3.13
Classifier: Programming Language :: Python :: 3.14
Classifier: Topic :: Internet
Requires-Dist: Django (>=4.2)
Project-URL: Repository, https://github.com/pixeldomain/django-datetime-utc
